vit_pytorch/__init__.py
vit_pytorch/lilvit.py
vit_pytorch_implementation-1.0.2.dist-info/METADATA
vit_pytorch_implementation-1.0.2.dist-info/WHEEL
vit_pytorch_implementation-1.0.2.dist-info/top_level.txt
vit_pytorch_implementation-1.0.2.dist-info/RECORD
