Metadata-Version: 2.1
Name: vit-pytorch-implementation
Version: 1.0.2
Summary: Vision Transformer (ViT) - Pytorch
Home-page: https://github.com/soumya1729/vit-pytorch-implementation/
Author: SM
License: MIT
Keywords: artificial intelligence,attention mechanism,image recognition
Classifier: Development Status :: 4 - Beta
Classifier: Intended Audience :: Developers
Classifier: Topic :: Scientific/Engineering :: Artificial Intelligence
Classifier: License :: OSI Approved :: MIT License
Classifier: Programming Language :: Python :: 3.6
Requires-Dist: einops >=0.7.0
Requires-Dist: torch >=1.10
Requires-Dist: torchvision
